bresenham/__init__.py
bresenham/bresenham.py
pybresenham_tspspi-0.0.2.dist-info/LICENSE.md
pybresenham_tspspi-0.0.2.dist-info/METADATA
pybresenham_tspspi-0.0.2.dist-info/WHEEL
pybresenham_tspspi-0.0.2.dist-info/top_level.txt
pybresenham_tspspi-0.0.2.dist-info/RECORD
