Metadata-Version: 2.1
Name: pybresenham-tspspi
Version: 0.0.2
Summary: A very simple implementation of Bresenham algorithm implementations
Home-page: https://github.com/tspspi/pybresenham
Author: Thomas Spielauer
Author-email: pypipackages01@tspi.at
Classifier: Programming Language :: Python :: 3
Classifier: License :: OSI Approved :: BSD License
Classifier: Operating System :: OS Independent
Requires-Python: >=3.8
License-File: LICENSE.md
Requires-Dist: numpy >=1.25
